Workbook

Sheet Imported_Raw_Data
A1: Raw Data
A2: transaction_id | B2: transaction_date | C2: customer_id | D2: customer_name | E2: customer_segment | F2: region | G2: channel | H2: product_category | I2: quantity | J2: unit_price | K2: revenue | L2: payment_method | M2: returned
A3: TXN100000 | B3: 45029 | C3: CUST1526 | D3: Customer_381 | E3: Consumer | F3: North | G3: Online | H3: Furniture | I3: 5 | J3: 35866.07 | K3: 179330.37 | L3: Cash | M3: Yes
A4: TXN100001 | B4: 45362 | C4: CUST1239 | D4: Customer_576 | E4: Corporate | F4: West | G4: Online | H4: Furniture | I4: 1 | J4: 34676.53 | K4: 34676.53 | L4: UPI | M4: No
A5: TXN100002 | B5: 45197 | C5: CUST1072 | D5: Customer_635 | E5: Consumer | F5: East | G5: Online | H5: Accessories | I5: 3 | J5: 1380.83 | K5: 4142.48 | L5: Card | M5: No
A6: TXN100003 | B6: 45033 | C6: CUST1445 | D6: Customer_254 | E6: Corporate | F6: North | G6: Online | H6: Furniture | I6: 1 | J6: 24873.14 | K6: 24873.14 | L6: Card | M6: No
A7: TXN100004 | B7: 44998 | C7: CUST1655 | D7: Customer_477 | E7: Consumer | F7: West | G7: Store | H7: Furniture | I7: 2 | J7: 27213.1 | K7: 54426.2 | L7: UPI | M7: No
A8: TXN100005 | B8: 44947 | C8: CUST1509 | D8: Customer_114 | E8: Corporate | F8: South | G8: Online | H8: Furniture | I8: 1 | J8: 35426.58 | K8: 35426.58 | L8: Cash | M8: No
A9: TXN100006 | B9: 45048 | C9: CUST1795 | D9: Customer_20 | E9: Consumer | F9: South | G9: Online | H9: Clothing | I9: 4 | J9: 1832.29 | K9: 7329.14 | L9: Card | M9: Yes
A10: TXN100007 | B10: 45393 | C10: CUST1269 | D10: Customer_528 | E10: Consumer | F10: West | G10: Store | H10: Accessories | I10: 4 | J10: 1226.98 | K10: 4907.93 | L10: Card | M10: No
A11: TXN100008 | B11: 45141 | C11: CUST1753 | D11: Customer_145 | E11: Corporate | F11: North | G11: Store | H11: Electronics | I11: 2 | J11: 17880.91 | K11: 35761.82 | L11: Card | M11: No
A12: TXN100009 | B12: 45257 | C12: CUST1415 | D12: Customer_208 | E12: Home Office | F12: West | G12: Store | H12: Electronics | I12: 1 | J12: 17091.06 | K12: 17091.06 | L12: Card | M12: No
A13: TXN100010 | B13: 45385 | C13: CUST1245 | D13: Customer_531 | E13: Corporate | F13: West | G13: Store | H13: Accessories | I13: 3 | J13: 1194.55 | K13: 3583.65 | L13: Card | M13: No
A14: TXN100011 | B14: 45014 | C14: CUST1675 | D14: Customer_376 | E14: Home Office | F14: North | G14: Online | H14: Clothing | I14: 2 | J14: 2867.47 | K14: 5734.94 | L14: Card | M14: Yes
... A4002: TXN103999 | B4002: 45292 | C4002: CUST1362 | D4002: Customer_525 | E4002: Consumer | F4002: North | G4002: Store | H4002: Clothing | I4002: 4 | J4002: 2131.3 | K4002: 8525.21 | L4002: UPI | M4002: No

Sheet Cleaned_Data
A1: transaction_id | B1: transaction_date | C1: customer_id | D1: customer_name | E1: customer_segment | F1: region | G1: channel | H1: product_category | I1: quantity | J1: unit_price | K1: revenue | L1: payment_method | M1: returned | N1: customer_first_flag | O1: return_flag | P1: month_key | Q1: cust_unique_filtered
A2: TXN100000 | B2: 45029 | C2: CUST1526 | D2: Customer_381 | E2: Consumer | F2: North | G2: Online | H2: Furniture | I2: 5 | J2: 35866.07 | K2: 179330.37 | L2: Cash | M2: Yes | N2: =IF(COUNTIF($C$2:C2,C2)=1,1,0) -> 1 | O2: =IF(OR(M2="Yes",M2="YES",M2=TRUE,M2=1),1,0) -> 1 | P2: =TEXT(B2,"yyyy-mm") -> 2023-04 | Q2: =IF(AND(IF(dashboard!$B$4="All",TRUE,$F2=dashboard!$B$4),IF(dashboard!$B$5="All",TRUE,$E2=dashboard!$B$5),IF(dashboard!$B$6="All",TRUE,$G2=dashboard!$B$6),IF(dashboard!$B$7="All",TRUE,$M2=dashboard!$B$7),$P2>=dashboard!$B$8,$P2<=dashboard!$B$9,COUNTIFS($C$2:C2,$C2,$F$2:F2,IF(dashboard!$B$4="All","*",dashboard!$B$4),$E$2:E2,IF(dashboard!$B$5="All","*",dashboard!$B$5),$G$2:G2,IF(dashboard!$B$6="All","*",dashboard!$B$6),$M$2:M2,IF(dashboard!$B$7="All","*",dashboard!$B$7),$P$2:P2,">="&dashboard!$B$8,$P$2:P2,"<="&dashboard!$B$9)=1),1,0) -> 0
A3: TXN100001 | B3: 45362 | C3: CUST1239 | D3: Customer_576 | E3: Corporate | F3: West | G3: Online | H3: Furniture | I3: 1 | J3: 34676.53 | K3: 34676.53 | L3: UPI | M3: No | N3: =IF(COUNTIF($C$2:C3,C3)=1,1,0) -> 1 | O3: =IF(OR(M3="Yes",M3="YES",M3=TRUE,M3=1),1,0) -> 0 | P3: =TEXT(B3,"yyyy-mm") -> 2024-03 | Q3: =IF(AND(IF(dashboard!$B$4="All",TRUE,$F3=dashboard!$B$4),IF(dashboard!$B$5="All",TRUE,$E3=dashboard!$B$5),IF(dashboard!$B$6="All",TRUE,$G3=dashboard!$B$6),IF(dashboard!$B$7="All",TRUE,$M3=dashboard!$B$7),$P3>=dashboard!$B$8,$P3<=dashboard!$B$9,COUNTIFS($C$2:C3,$C3,$F$2:F3,IF(dashboard!$B$4="All","*",dashboard!$B$4),$E$2:E3,IF(dashboard!$B$5="All","*",dashboard!$B$5),$G$2:G3,IF(dashboard!$B$6="All","*",dashboard!$B$6),$M$2:M3,IF(dashboard!$B$7="All","*",dashboard!$B$7),$P$2:P3,">="&dashboard!$B$8,$P$2:P3,"<="&dashboard!$B$9)=1),1,0) -> 0
A4: TXN100002 | B4: 45197 | C4: CUST1072 | D4: Customer_635 | E4: Consumer | F4: East | G4: Online | H4: Accessories | I4: 3 | J4: 1380.83 | K4: 4142.48 | L4: Card | M4: No | N4: =IF(COUNTIF($C$2:C4,C4)=1,1,0) -> 1 | O4: =IF(OR(M4="Yes",M4="YES",M4=TRUE,M4=1),1,0) -> 0 | P4: =TEXT(B4,"yyyy-mm") -> 2023-09 | Q4: =IF(AND(IF(dashboard!$B$4="All",TRUE,$F4=dashboard!$B$4),IF(dashboard!$B$5="All",TRUE,$E4=dashboard!$B$5),IF(dashboard!$B$6="All",TRUE,$G4=dashboard!$B$6),IF(dashboard!$B$7="All",TRUE,$M4=dashboard!$B$7),$P4>=dashboard!$B$8,$P4<=dashboard!$B$9,COUNTIFS($C$2:C4,$C4,$F$2:F4,IF(dashboard!$B$4="All","*",dashboard!$B$4),$E$2:E4,IF(dashboard!$B$5="All","*",dashboard!$B$5),$G$2:G4,IF(dashboard!$B$6="All","*",dashboard!$B$6),$M$2:M4,IF(dashboard!$B$7="All","*",dashboard!$B$7),$P$2:P4,">="&dashboard!$B$8,$P$2:P4,"<="&dashboard!$B$9)=1),1,0) -> 1
A5: TXN100003 | B5: 45033 | C5: CUST1445 | D5: Customer_254 | E5: Corporate | F5: North | G5: Online | H5: Furniture | I5: 1 | J5: 24873.14 | K5: 24873.14 | L5: Card | M5: No | N5: =IF(COUNTIF($C$2:C5,C5)=1,1,0) -> 1 | O5: =IF(OR(M5="Yes",M5="YES",M5=TRUE,M5=1),1,0) -> 0 | P5: =TEXT(B5,"yyyy-mm") -> 2023-04 | Q5: =IF(AND(IF(dashboard!$B$4="All",TRUE,$F5=dashboard!$B$4),IF(dashboard!$B$5="All",TRUE,$E5=dashboard!$B$5),IF(dashboard!$B$6="All",TRUE,$G5=dashboard!$B$6),IF(dashboard!$B$7="All",TRUE,$M5=dashboard!$B$7),$P5>=dashboard!$B$8,$P5<=dashboard!$B$9,COUNTIFS($C$2:C5,$C5,$F$2:F5,IF(dashboard!$B$4="All","*",dashboard!$B$4),$E$2:E5,IF(dashboard!$B$5="All","*",dashboard!$B$5),$G$2:G5,IF(dashboard!$B$6="All","*",dashboard!$B$6),$M$2:M5,IF(dashboard!$B$7="All","*",dashboard!$B$7),$P$2:P5,">="&dashboard!$B$8,$P$2:P5,"<="&dashboard!$B$9)=1),1,0) -> 0
A6: TXN100004 | B6: 44998 | C6: CUST1655 | D6: Customer_477 | E6: Consumer | F6: West | G6: Store | H6: Furniture | I6: 2 | J6: 27213.1 | K6: 54426.2 | L6: UPI | M6: No | N6: =IF(COUNTIF($C$2:C6,C6)=1,1,0) -> 1 | O6: =IF(OR(M6="Yes",M6="YES",M6=TRUE,M6=1),1,0) -> 0 | P6: =TEXT(B6,"yyyy-mm") -> 2023-03 | Q6: =IF(AND(IF(dashboard!$B$4="All",TRUE,$F6=dashboard!$B$4),IF(dashboard!$B$5="All",TRUE,$E6=dashboard!$B$5),IF(dashboard!$B$6="All",TRUE,$G6=dashboard!$B$6),IF(dashboard!$B$7="All",TRUE,$M6=dashboard!$B$7),$P6>=dashboard!$B$8,$P6<=dashboard!$B$9,COUNTIFS($C$2:C6,$C6,$F$2:F6,IF(dashboard!$B$4="All","*",dashboard!$B$4),$E$2:E6,IF(dashboard!$B$5="All","*",dashboard!$B$5),$G$2:G6,IF(dashboard!$B$6="All","*",dashboard!$B$6),$M$2:M6,IF(dashboard!$B$7="All","*",dashboard!$B$7),$P$2:P6,">="&dashboard!$B$8,$P$2:P6,"<="&dashboard!$B$9)=1),1,0) -> 0
A7: TXN100005 | B7: 44947 | C7: CUST1509 | D7: Customer_114 | E7: Corporate | F7: South | G7: Online | H7: Furniture | I7: 1 | J7: 35426.58 | K7: 35426.58 | L7: Cash | M7: No | N7: =IF(COUNTIF($C$2:C7,C7)=1,1,0) -> 1 | O7: =IF(OR(M7="Yes",M7="YES",M7=TRUE,M7=1),1,0) -> 0 | P7: =TEXT(B7,"yyyy-mm") -> 2023-01 | Q7: =IF(AND(IF(dashboard!$B$4="All",TRUE,$F7=dashboard!$B$4),IF(dashboard!$B$5="All",TRUE,$E7=dashboard!$B$5),IF(dashboard!$B$6="All",TRUE,$G7=dashboard!$B$6),IF(dashboard!$B$7="All",TRUE,$M7=dashboard!$B$7),$P7>=dashboard!$B$8,$P7<=dashboard!$B$9,COUNTIFS($C$2:C7,$C7,$F$2:F7,IF(dashboard!$B$4="All","*",dashboard!$B$4),$E$2:E7,IF(dashboard!$B$5="All","*",dashboard!$B$5),$G$2:G7,IF(dashboard!$B$6="All","*",dashboard!$B$6),$M$2:M7,IF(dashboard!$B$7="All","*",dashboard!$B$7),$P$2:P7,">="&dashboard!$B$8,$P$2:P7,"<="&dashboard!$B$9)=1),1,0) -> 0
A8: TXN100006 | B8: 45048 | C8: CUST1795 | D8: Customer_20 | E8: Consumer | F8: South | G8: Online | H8: Clothing | I8: 4 | J8: 1832.29 | K8: 7329.14 | L8: Card | M8: Yes | N8: =IF(COUNTIF($C$2:C8,C8)=1,1,0) -> 1 | O8: =IF(OR(M8="Yes",M8="YES",M8=TRUE,M8=1),1,0) -> 1 | P8: =TEXT(B8,"yyyy-mm") -> 2023-05 | Q8: =IF(AND(IF(dashboard!$B$4="All",TRUE,$F8=dashboard!$B$4),IF(dashboard!$B$5="All",TRUE,$E8=dashboard!$B$5),IF(dashboard!$B$6="All",TRUE,$G8=dashboard!$B$6),IF(dashboard!$B$7="All",TRUE,$M8=dashboard!$B$7),$P8>=dashboard!$B$8,$P8<=dashboard!$B$9,COUNTIFS($C$2:C8,$C8,$F$2:F8,IF(dashboard!$B$4="All","*",dashboard!$B$4),$E$2:E8,IF(dashboard!$B$5="All","*",dashboard!$B$5),$G$2:G8,IF(dashboard!$B$6="All","*",dashboard!$B$6),$M$2:M8,IF(dashboard!$B$7="All","*",dashboard!$B$7),$P$2:P8,">="&dashboard!$B$8,$P$2:P8,"<="&dashboard!$B$9)=1),1,0) -> 0
A9: TXN100007 | B9: 45393 | C9: CUST1269 | D9: Customer_528 | E9: Consumer | F9: West | G9: Store | H9: Accessories | I9: 4 | J9: 1226.98 | K9: 4907.93 | L9: Card | M9: No | N9: =IF(COUNTIF($C$2:C9,C9)=1,1,0) -> 1 | O9: =IF(OR(M9="Yes",M9="YES",M9=TRUE,M9=1),1,0) -> 0 | P9: =TEXT(B9,"yyyy-mm") -> 2024-04 | Q9: =IF(AND(IF(dashboard!$B$4="All",TRUE,$F9=dashboard!$B$4),IF(dashboard!$B$5="All",TRUE,$E9=dashboard!$B$5),IF(dashboard!$B$6="All",TRUE,$G9=dashboard!$B$6),IF(dashboard!$B$7="All",TRUE,$M9=dashboard!$B$7),$P9>=dashboard!$B$8,$P9<=dashboard!$B$9,COUNTIFS($C$2:C9,$C9,$F$2:F9,IF(dashboard!$B$4="All","*",dashboard!$B$4),$E$2:E9,IF(dashboard!$B$5="All","*",dashboard!$B$5),$G$2:G9,IF(dashboard!$B$6="All","*",dashboard!$B$6),$M$2:M9,IF(dashboard!$B$7="All","*",dashboard!$B$7),$P$2:P9,">="&dashboard!$B$8,$P$2:P9,"<="&dashboard!$B$9)=1),1,0) -> 0
A10: TXN100008 | B10: 45141 | C10: CUST1753 | D10: Customer_145 | E10: Corporate | F10: North | G10: Store | H10: Electronics | I10: 2 | J10: 17880.91 | K10: 35761.82 | L10: Card | M10: No | N10: =IF(COUNTIF($C$2:C10,C10)=1,1,0) -> 1 | O10: =IF(OR(M10="Yes",M10="YES",M10=TRUE,M10=1),1,0) -> 0 | P10: =TEXT(B10,"yyyy-mm") -> 2023-08 | Q10: =IF(AND(IF(dashboard!$B$4="All",TRUE,$F10=dashboard!$B$4),IF(dashboard!$B$5="All",TRUE,$E10=dashboard!$B$5),IF(dashboard!$B$6="All",TRUE,$G10=dashboard!$B$6),IF(dashboard!$B$7="All",TRUE,$M10=dashboard!$B$7),$P10>=dashboard!$B$8,$P10<=dashboard!$B$9,COUNTIFS($C$2:C10,$C10,$F$2:F10,IF(dashboard!$B$4="All","*",dashboard!$B$4),$E$2:E10,IF(dashboard!$B$5="All","*",dashboard!$B$5),$G$2:G10,IF(dashboard!$B$6="All","*",dashboard!$B$6),$M$2:M10,IF(dashboard!$B$7="All","*",dashboard!$B$7),$P$2:P10,">="&dashboard!$B$8,$P$2:P10,"<="&dashboard!$B$9)=1),1,0) -> 0
A11: TXN100009 | B11: 45257 | C11: CUST1415 | D11: Customer_208 | E11: Home Office | F11: West | G11: Store | H11: Electronics | I11: 1 | J11: 17091.06 | K11: 17091.06 | L11: Card | M11: No | N11: =IF(COUNTIF($C$2:C11,C11)=1,1,0) -> 1 | O11: =IF(OR(M11="Yes",M11="YES",M11=TRUE,M11=1),1,0) -> 0 | P11: =TEXT(B11,"yyyy-mm") -> 2023-11 | Q11: =IF(AND(IF(dashboard!$B$4="All",TRUE,$F11=dashboard!$B$4),IF(dashboard!$B$5="All",TRUE,$E11=dashboard!$B$5),IF(dashboard!$B$6="All",TRUE,$G11=dashboard!$B$6),IF(dashboard!$B$7="All",TRUE,$M11=dashboard!$B$7),$P11>=dashboard!$B$8,$P11<=dashboard!$B$9,COUNTIFS($C$2:C11,$C11,$F$2:F11,IF(dashboard!$B$4="All","*",dashboard!$B$4),$E$2:E11,IF(dashboard!$B$5="All","*",dashboard!$B$5),$G$2:G11,IF(dashboard!$B$6="All","*",dashboard!$B$6),$M$2:M11,IF(dashboard!$B$7="All","*",dashboard!$B$7),$P$2:P11,">="&dashboard!$B$8,$P$2:P11,"<="&dashboard!$B$9)=1),1,0) -> 0
A12: TXN100010 | B12: 45385 | C12: CUST1245 | D12: Customer_531 | E12: Corporate | F12: West | G12: Store | H12: Accessories | I12: 3 | J12: 1194.55 | K12: 3583.65 | L12: Card | M12: No | N12: =IF(COUNTIF($C$2:C12,C12)=1,1,0) -> 1 | O12: =IF(OR(M12="Yes",M12="YES",M12=TRUE,M12=1),1,0) -> 0 | P12: =TEXT(B12,"yyyy-mm") -> 2024-04 | Q12: =IF(AND(IF(dashboard!$B$4="All",TRUE,$F12=dashboard!$B$4),IF(dashboard!$B$5="All",TRUE,$E12=dashboard!$B$5),IF(dashboard!$B$6="All",TRUE,$G12=dashboard!$B$6),IF(dashboard!$B$7="All",TRUE,$M12=dashboard!$B$7),$P12>=dashboard!$B$8,$P12<=dashboard!$B$9,COUNTIFS($C$2:C12,$C12,$F$2:F12,IF(dashboard!$B$4="All","*",dashboard!$B$4),$E$2:E12,IF(dashboard!$B$5="All","*",dashboard!$B$5),$G$2:G12,IF(dashboard!$B$6="All","*",dashboard!$B$6),$M$2:M12,IF(dashboard!$B$7="All","*",dashboard!$B$7),$P$2:P12,">="&dashboard!$B$8,$P$2:P12,"<="&dashboard!$B$9)=1),1,0) -> 0
A13: TXN100011 | B13: 45014 | C13: CUST1675 | D13: Customer_376 | E13: Home Office | F13: North | G13: Online | H13: Clothing | I13: 2 | J13: 2867.47 | K13: 5734.94 | L13: Card | M13: Yes | N13: =IF(COUNTIF($C$2:C13,C13)=1,1,0) -> 1 | O13: =IF(OR(M13="Yes",M13="YES",M13=TRUE,M13=1),1,0) -> 1 | P13: =TEXT(B13,"yyyy-mm") -> 2023-03 | Q13: =IF(AND(IF(dashboard!$B$4="All",TRUE,$F13=dashboard!$B$4),IF(dashboard!$B$5="All",TRUE,$E13=dashboard!$B$5),IF(dashboard!$B$6="All",TRUE,$G13=dashboard!$B$6),IF(dashboard!$B$7="All",TRUE,$M13=dashboard!$B$7),$P13>=dashboard!$B$8,$P13<=dashboard!$B$9,COUNTIFS($C$2:C13,$C13,$F$2:F13,IF(dashboard!$B$4="All","*",dashboard!$B$4),$E$2:E13,IF(dashboard!$B$5="All","*",dashboard!$B$5),$G$2:G13,IF(dashboard!$B$6="All","*",dashboard!$B$6),$M$2:M13,IF(dashboard!$B$7="All","*",dashboard!$B$7),$P$2:P13,">="&dashboard!$B$8,$P$2:P13,"<="&dashboard!$B$9)=1),1,0) -> 0
... A4001: TXN103999 | B4001: 45292 | C4001: CUST1362 | D4001: Customer_525 | E4001: Consumer | F4001: North | G4001: Store | H4001: Clothing | I4001: 4 | J4001: 2131.3 | K4001: 8525.21 | L4001: UPI | M4001: No | N4001: =IF(COUNTIF($C$2:C4001,C4001)=1,1,0) -> 0 | O4001: =IF(OR(M4001="Yes",M4001="YES",M4001=TRUE,M4001=1),1,0) -> 0 | P4001: =TEXT(B4001,"yyyy-mm") -> 2024-01 | Q4001: =IF(AND(IF(dashboard!$B$4="All",TRUE,$F4001=dashboard!$B$4),IF(dashboard!$B$5="All",TRUE,$E4001=dashboard!$B$5),IF(dashboard!$B$6="All",TRUE,$G4001=dashboard!$B$6),IF(dashboard!$B$7="All",TRUE,$M4001=dashboard!$B$7),$P4001>=dashboard!$B$8,$P4001<=dashboard!$B$9,COUNTIFS($C$2:C4001,$C4001,$F$2:F4001,IF(dashboard!$B$4="All","*",dashboard!$B$4),$E$2:E4001,IF(dashboard!$B$5="All","*",dashboard!$B$5),$G$2:G4001,IF(dashboard!$B$6="All","*",dashboard!$B$6),$M$2:M4001,IF(dashboard!$B$7="All","*",dashboard!$B$7),$P$2:P4001,">="&dashboard!$B$8,$P$2:P4001,"<="&dashboard!$B$9)=1),1,0) -> 0

Sheet Metrics
A1: Phase 3/4 Metrics (computed from Cleaned_Data table)
A3: Metric | B3: Value
A4: Total Revenue | B4: =SUM(Cleaned_Data!$K$2:$K$4001) -> 1.5197094e+08
A5: Total Transactions | B5: =COUNTA(Cleaned_Data!$A$2:$A$4001) -> 4000
A6: Total Customers (Distinct) | B6: =SUM(Cleaned_Data!$N$2:$N$4001) -> 796
A7: Avg Revenue / Transaction | B7: =IF(B5=0,"",B4/B5) -> 37992.734
A8: Return Rate % | B8: =IF(B5=0,"",SUM(Cleaned_Data!$O$2:$O$4001)/B5) -> 0.12375

Sheet Input_Metrics_CSV
A1: Provided metrics (from retail_analysis_metrics.csv)
A3: dimension | B3: key | C3: metric | D3: value
A4: KPI | B4: All | C4: Total Revenue | D4: 1.5197094e+08
A5: KPI | B5: All | C5: Total Transactions | D5: 4000
A6: KPI | B6: All | C6: Total Unique Customers | D6: 796
A7: KPI | B7: All | C7: Avg Revenue per Transaction | D7: 37992.734
A8: Segment | B8: Consumer | C8: total_revenue | D8: 82488410
A9: Segment | B9: Corporate | C9: total_revenue | D9: 45549211
A10: Segment | B10: Home Office | C10: total_revenue | D10: 23933317
A11: Segment | B11: Consumer | C11: transactions | D11: 2204
A12: Segment | B12: Corporate | C12: transactions | D12: 1189
A13: Segment | B13: Home Office | C13: transactions | D13: 607
A14: Segment | B14: Consumer | C14: avg_revenue_per_transaction | D14: 37426.683
A15: Segment | B15: Corporate | C15: avg_revenue_per_transaction | D15: 38308.84
... A27: Channel | B27: Store | C27: revenue_share | D27: 0.39404071

Sheet Pivot_Segment_by_Region
A1: Segment × Region Revenue
A3: Segment | B3: East | C3: North | D3: South | E3: West | F3: Grand Total
A4: Consumer | B4: =SUMIFS(Cleaned_Data!$K$2:$K$4001,Cleaned_Data!$E$2:$E$4001,$A4,Cleaned_Data!$F$2:$F$4001,B$3) -> 20366712 | C4: =SUMIFS(Cleaned_Data!$K$2:$K$4001,Cleaned_Data!$E$2:$E$4001,$A4,Cleaned_Data!$F$2:$F$4001,C$3) -> 18936800 | D4: =SUMIFS(Cleaned_Data!$K$2:$K$4001,Cleaned_Data!$E$2:$E$4001,$A4,Cleaned_Data!$F$2:$F$4001,D$3) -> 20212024 | E4: =SUMIFS(Cleaned_Data!$K$2:$K$4001,Cleaned_Data!$E$2:$E$4001,$A4,Cleaned_Data!$F$2:$F$4001,E$3) -> 22972874 | F4: =SUM(B4:E4) -> 82488410
A5: Corporate | B5: =SUMIFS(Cleaned_Data!$K$2:$K$4001,Cleaned_Data!$E$2:$E$4001,$A5,Cleaned_Data!$F$2:$F$4001,B$3) -> 10895017 | C5: =SUMIFS(Cleaned_Data!$K$2:$K$4001,Cleaned_Data!$E$2:$E$4001,$A5,Cleaned_Data!$F$2:$F$4001,C$3) -> 11324746 | D5: =SUMIFS(Cleaned_Data!$K$2:$K$4001,Cleaned_Data!$E$2:$E$4001,$A5,Cleaned_Data!$F$2:$F$4001,D$3) -> 12964881 | E5: =SUMIFS(Cleaned_Data!$K$2:$K$4001,Cleaned_Data!$E$2:$E$4001,$A5,Cleaned_Data!$F$2:$F$4001,E$3) -> 10364566 | F5: =SUM(B5:E5) -> 45549211
A6: Home Office | B6: =SUMIFS(Cleaned_Data!$K$2:$K$4001,Cleaned_Data!$E$2:$E$4001,$A6,Cleaned_Data!$F$2:$F$4001,B$3) -> 5520621.7 | C6: =SUMIFS(Cleaned_Data!$K$2:$K$4001,Cleaned_Data!$E$2:$E$4001,$A6,Cleaned_Data!$F$2:$F$4001,C$3) -> 5936626.1 | D6: =SUMIFS(Cleaned_Data!$K$2:$K$4001,Cleaned_Data!$E$2:$E$4001,$A6,Cleaned_Data!$F$2:$F$4001,D$3) -> 6356158 | E6: =SUMIFS(Cleaned_Data!$K$2:$K$4001,Cleaned_Data!$E$2:$E$4001,$A6,Cleaned_Data!$F$2:$F$4001,E$3) -> 6119911.1 | F6: =SUM(B6:E6) -> 23933317
A7: Grand Total | B7: =SUM(B4:B6) -> 36782351 | C7: =SUM(C4:C6) -> 36198173 | D7: =SUM(D4:D6) -> 39533063 | E7: =SUM(E4:E6) -> 39457351 | F7: =SUM(B7:E7) -> 1.5197094e+08

Sheet Pivot_Monthly_Trend
A1: Monthly Revenue Trend
A3: Month | B3: Revenue | C3: Transactions | D3: Avg Rev/Txn | E3: Return Rate %
A4: 2023-01 | B4: =SUMIFS(Cleaned_Data!$K$2:$K$4001,Cleaned_Data!$P$2:$P$4001,$A4) -> 9574177.4 | C4: =COUNTIFS(Cleaned_Data!$P$2:$P$4001,$A4) -> 230 | D4: =IF(C4=0,"",B4/C4) -> 41626.858 | E4: =IF(C4=0,"",SUMIFS(Cleaned_Data!$O$2:$O$4001,Cleaned_Data!$P$2:$P$4001,$A4)/C4) -> 0.1173913
A5: 2023-02 | B5: =SUMIFS(Cleaned_Data!$K$2:$K$4001,Cleaned_Data!$P$2:$P$4001,$A5) -> 7819785.9 | C5: =COUNTIFS(Cleaned_Data!$P$2:$P$4001,$A5) -> 197 | D5: =IF(C5=0,"",B5/C5) -> 39694.345 | E5: =IF(C5=0,"",SUMIFS(Cleaned_Data!$O$2:$O$4001,Cleaned_Data!$P$2:$P$4001,$A5)/C5) -> 0.16243655
A6: 2023-03 | B6: =SUMIFS(Cleaned_Data!$K$2:$K$4001,Cleaned_Data!$P$2:$P$4001,$A6) -> 9145646.2 | C6: =COUNTIFS(Cleaned_Data!$P$2:$P$4001,$A6) -> 217 | D6: =IF(C6=0,"",B6/C6) -> 42145.835 | E6: =IF(C6=0,"",SUMIFS(Cleaned_Data!$O$2:$O$4001,Cleaned_Data!$P$2:$P$4001,$A6)/C6) -> 0.11520737
A7: 2023-04 | B7: =SUMIFS(Cleaned_Data!$K$2:$K$4001,Cleaned_Data!$P$2:$P$4001,$A7) -> 8846989.2 | C7: =COUNTIFS(Cleaned_Data!$P$2:$P$4001,$A7) -> 242 | D7: =IF(C7=0,"",B7/C7) -> 36557.807 | E7: =IF(C7=0,"",SUMIFS(Cleaned_Data!$O$2:$O$4001,Cleaned_Data!$P$2:$P$4001,$A7)/C7) -> 0.11983471
A8: 2023-05 | B8: =SUMIFS(Cleaned_Data!$K$2:$K$4001,Cleaned_Data!$P$2:$P$4001,$A8) -> 9308053.1 | C8: =COUNTIFS(Cleaned_Data!$P$2:$P$4001,$A8) -> 225 | D8: =IF(C8=0,"",B8/C8) -> 41369.125 | E8: =IF(C8=0,"",SUMIFS(Cleaned_Data!$O$2:$O$4001,Cleaned_Data!$P$2:$P$4001,$A8)/C8) -> 0.18222222
A9: 2023-06 | B9: =SUMIFS(Cleaned_Data!$K$2:$K$4001,Cleaned_Data!$P$2:$P$4001,$A9) -> 8705807.6 | C9: =COUNTIFS(Cleaned_Data!$P$2:$P$4001,$A9) -> 215 | D9: =IF(C9=0,"",B9/C9) -> 40492.128 | E9: =IF(C9=0,"",SUMIFS(Cleaned_Data!$O$2:$O$4001,Cleaned_Data!$P$2:$P$4001,$A9)/C9) -> 0.093023256
A10: 2023-07 | B10: =SUMIFS(Cleaned_Data!$K$2:$K$4001,Cleaned_Data!$P$2:$P$4001,$A10) -> 9741507.2 | C10: =COUNTIFS(Cleaned_Data!$P$2:$P$4001,$A10) -> 235 | D10: =IF(C10=0,"",B10/C10) -> 41453.222 | E10: =IF(C10=0,"",SUMIFS(Cleaned_Data!$O$2:$O$4001,Cleaned_Data!$P$2:$P$4001,$A10)/C10) -> 0.10212766
A11: 2023-08 | B11: =SUMIFS(Cleaned_Data!$K$2:$K$4001,Cleaned_Data!$P$2:$P$4001,$A11) -> 8775407 | C11: =COUNTIFS(Cleaned_Data!$P$2:$P$4001,$A11) -> 240 | D11: =IF(C11=0,"",B11/C11) -> 36564.196 | E11: =IF(C11=0,"",SUMIFS(Cleaned_Data!$O$2:$O$4001,Cleaned_Data!$P$2:$P$4001,$A11)/C11) -> 0.15833333
A12: 2023-09 | B12: =SUMIFS(Cleaned_Data!$K$2:$K$4001,Cleaned_Data!$P$2:$P$4001,$A12) -> 7657147.6 | C12: =COUNTIFS(Cleaned_Data!$P$2:$P$4001,$A12) -> 210 | D12: =IF(C12=0,"",B12/C12) -> 36462.608 | E12: =IF(C12=0,"",SUMIFS(Cleaned_Data!$O$2:$O$4001,Cleaned_Data!$P$2:$P$4001,$A12)/C12) -> 0.1
A13: 2023-10 | B13: =SUMIFS(Cleaned_Data!$K$2:$K$4001,Cleaned_Data!$P$2:$P$4001,$A13) -> 7936710.9 | C13: =COUNTIFS(Cleaned_Data!$P$2:$P$4001,$A13) -> 226 | D13: =IF(C13=0,"",B13/C13) -> 35118.19 | E13: =IF(C13=0,"",SUMIFS(Cleaned_Data!$O$2:$O$4001,Cleaned_Data!$P$2:$P$4001,$A13)/C13) -> 0.12831858
A14: 2023-11 | B14: =SUMIFS(Cleaned_Data!$K$2:$K$4001,Cleaned_Data!$P$2:$P$4001,$A14) -> 7857412.8 | C14: =COUNTIFS(Cleaned_Data!$P$2:$P$4001,$A14) -> 196 | D14: =IF(C14=0,"",B14/C14) -> 40088.841 | E14: =IF(C14=0,"",SUMIFS(Cleaned_Data!$O$2:$O$4001,Cleaned_Data!$P$2:$P$4001,$A14)/C14) -> 0.11734694
A15: 2023-12 | B15: =SUMIFS(Cleaned_Data!$K$2:$K$4001,Cleaned_Data!$P$2:$P$4001,$A15) -> 8769390.3 | C15: =COUNTIFS(Cleaned_Data!$P$2:$P$4001,$A15) -> 237 | D15: =IF(C15=0,"",B15/C15) -> 37001.647 | E15: =IF(C15=0,"",SUMIFS(Cleaned_Data!$O$2:$O$4001,Cleaned_Data!$P$2:$P$4001,$A15)/C15) -> 0.10970464
... A21: 2024-06 | B21: =SUMIFS(Cleaned_Data!$K$2:$K$4001,Cleaned_Data!$P$2:$P$4001,$A21) -> 7028295.5 | C21: =COUNTIFS(Cleaned_Data!$P$2:$P$4001,$A21) -> 197 | D21: =IF(C21=0,"",B21/C21) -> 35676.627 | E21: =IF(C21=0,"",SUMIFS(Cleaned_Data!$O$2:$O$4001,Cleaned_Data!$P$2:$P$4001,$A21)/C21) -> 0.12690355

Sheet dashboard
A1: Retail Sales Dashboard
A3: Filters | F3: Key Metrics (based on filters)
A4: Region | B4: East | F4: Total Revenue | I4: Total Transactions | L4: Return Rate
A5: Customer Segment | B5: All
A6: Channel | B6: All | F6: =Dashboard_Data!I2 -> 36782351 | I6: =Dashboard_Data!I3 -> 987 | L6: =Dashboard_Data!I6 -> 0.1195542
A7: Returned | B7: All
A8: From Month | B8: 2023-01 | F8: Distinct Customers | I8: Avg Rev / Transaction | L8: Avg Rev / Customer
A9: To Month | B9: 2024-06
F10: =Dashboard_Data!I4 -> 570 | I10: =Dashboard_Data!I7 -> 37266.819 | L10: =Dashboard_Data!I8 -> 64530.44
A12: Monthly Revenue Trend | H12: Revenue by Category
A29: Channel Contribution | H29: Revenue by Region & Segment

Sheet Charts

Sheet Pivot_Category
A1: Revenue by Product Category
A3: Category | B3: Revenue | C3: Transactions | D3: Avg Rev/Txn | E3: Return Rate %
A4: Accessories | B4: =SUMIFS(Cleaned_Data!$K$2:$K$4001,Cleaned_Data!$H$2:$H$4001,$A4) -> 3635659.7 | C4: =COUNTIFS(Cleaned_Data!$H$2:$H$4001,$A4) -> 1029 | D4: =IF(C4=0,"",B4/C4) -> 3533.197 | E4: =IF(C4=0,"",SUMIFS(Cleaned_Data!$O$2:$O$4001,Cleaned_Data!$H$2:$H$4001,$A4)/C4) -> 0.11953353
A5: Clothing | B5: =SUMIFS(Cleaned_Data!$K$2:$K$4001,Cleaned_Data!$H$2:$H$4001,$A5) -> 7610248.8 | C5: =COUNTIFS(Cleaned_Data!$H$2:$H$4001,$A5) -> 1044 | D5: =IF(C5=0,"",B5/C5) -> 7289.5103 | E5: =IF(C5=0,"",SUMIFS(Cleaned_Data!$O$2:$O$4001,Cleaned_Data!$H$2:$H$4001,$A5)/C5) -> 0.12835249
A6: Electronics | B6: =SUMIFS(Cleaned_Data!$K$2:$K$4001,Cleaned_Data!$H$2:$H$4001,$A6) -> 41953307 | C6: =COUNTIFS(Cleaned_Data!$H$2:$H$4001,$A6) -> 956 | D6: =IF(C6=0,"",B6/C6) -> 43884.213 | E6: =IF(C6=0,"",SUMIFS(Cleaned_Data!$O$2:$O$4001,Cleaned_Data!$H$2:$H$4001,$A6)/C6) -> 0.12761506
A7: Furniture | B7: =SUMIFS(Cleaned_Data!$K$2:$K$4001,Cleaned_Data!$H$2:$H$4001,$A7) -> 98771722 | C7: =COUNTIFS(Cleaned_Data!$H$2:$H$4001,$A7) -> 971 | D7: =IF(C7=0,"",B7/C7) -> 101721.65 | E7: =IF(C7=0,"",SUMIFS(Cleaned_Data!$O$2:$O$4001,Cleaned_Data!$H$2:$H$4001,$A7)/C7) -> 0.11946447
A8: Grand Total | B8: =SUM(B4:B7) -> 1.5197094e+08 | C8: =SUM(C4:C7) -> 4000 | D8: =IF(C8=0,"",B8/C8) -> 37992.734 | E8: =IF(C8=0,"",SUM(Cleaned_Data!$O$2:$O$4001)/C8) -> 0.12375

Sheet Pivot_Channel
A1: Revenue by Channel
A3: Channel | B3: Revenue | C3: Transactions | D3: Avg Rev/Txn | E3: Return Rate %
A4: Online | B4: =SUMIFS(Cleaned_Data!$K$2:$K$4001,Cleaned_Data!$G$2:$G$4001,$A4) -> 92088201 | C4: =COUNTIFS(Cleaned_Data!$G$2:$G$4001,$A4) -> 2338 | D4: =IF(C4=0,"",B4/C4) -> 39387.597 | E4: =IF(C4=0,"",SUMIFS(Cleaned_Data!$O$2:$O$4001,Cleaned_Data!$G$2:$G$4001,$A4)/C4) -> 0.11933276
A5: Store | B5: =SUMIFS(Cleaned_Data!$K$2:$K$4001,Cleaned_Data!$G$2:$G$4001,$A5) -> 59882737 | C5: =COUNTIFS(Cleaned_Data!$G$2:$G$4001,$A5) -> 1662 | D5: =IF(C5=0,"",B5/C5) -> 36030.528 | E5: =IF(C5=0,"",SUMIFS(Cleaned_Data!$O$2:$O$4001,Cleaned_Data!$G$2:$G$4001,$A5)/C5) -> 0.1299639

Sheet Pivot_Returns
A1: Returns Summary
A3: Returned | B3: Transactions | C3: Revenue | D3: Avg Rev/Txn
A4: Yes | B4: =COUNTIFS(Cleaned_Data!$M$2:$M$4001,$A4) -> 495 | C4: =SUMIFS(Cleaned_Data!$K$2:$K$4001,Cleaned_Data!$M$2:$M$4001,$A4) -> 18045273 | D4: =IF(B4=0,"",C4/B4) -> 36455.096
A5: No | B5: =COUNTIFS(Cleaned_Data!$M$2:$M$4001,$A5) -> 3505 | C5: =SUMIFS(Cleaned_Data!$K$2:$K$4001,Cleaned_Data!$M$2:$M$4001,$A5) -> 1.3392566e+08 | D5: =IF(B5=0,"",C5/B5) -> 38209.89

Sheet Dashboard_Data
A1: Months | C1: Regions | D1: Segments | E1: Channels | F1: Returns | G1: Categories | H1: KPI Label | I1: KPI Value | J1: Helper | M1: Month | N1: Revenue | P1: Category | Q1: Revenue | S1: Channel | T1: Revenue | V1: Region | W1: Consumer | X1: Corporate | Y1: Home Office
A2: All | C2: All | D2: All | E2: All | F2: All | G2: All | H2: Total Revenue | I2: =SUMIFS(Cleaned_Data!$K$2:$K$4001,Cleaned_Data!$F$2:$F$4001,$K$2,Cleaned_Data!$E$2:$E$4001,$K$3,Cleaned_Data!$G$2:$G$4001,$K$4,Cleaned_Data!$M$2:$M$4001,$K$5,Cleaned_Data!$P$2:$P$4001,">="&$K$6,Cleaned_Data!$P$2:$P$4001,"<="&$K$7) -> 36782351 | J2: Region_Crit | K2: =IF(dashboard!$B$4="All","*",dashboard!$B$4) -> East | M2: (all months) | P2: Accessories | Q2: =SUMIFS(Cleaned_Data!$K$2:$K$4001,Cleaned_Data!$F$2:$F$4001,$K$2,Cleaned_Data!$E$2:$E$4001,$K$3,Cleaned_Data!$G$2:$G$4001,$K$4,Cleaned_Data!$M$2:$M$4001,$K$5,Cleaned_Data!$P$2:$P$4001,">="&$K$6,Cleaned_Data!$P$2:$P$4001,"<="&$K$7,Cleaned_Data!$H$2:$H$4001,P2) -> 884141.89 | S2: Online | T2: =IF(OR(dashboard!$B$6="All",dashboard!$B$6=S2),SUMIFS(Cleaned_Data!$K$2:$K$4001,Cleaned_Data!$F$2:$F$4001,$K$2,Cleaned_Data!$E$2:$E$4001,$K$3,Cleaned_Data!$G$2:$G$4001,S2,Cleaned_Data!$M$2:$M$4001,$K$5,Cleaned_Data!$P$2:$P$4001,">="&$K$6,Cleaned_Data!$P$2:$P$4001,"<="&$K$7),NA()) -> 22279503 | V2: East | W2: =IF(AND(OR(dashboard!$B$4="All",dashboard!$B$4=V2),OR(dashboard!$B$5="All",dashboard!$B$5=W$1)),SUMIFS(Cleaned_Data!$K$2:$K$4001,Cleaned_Data!$F$2:$F$4001,V2,Cleaned_Data!$E$2:$E$4001,W$1,Cleaned_Data!$G$2:$G$4001,$K$4,Cleaned_Data!$M$2:$M$4001,$K$5,Cleaned_Data!$P$2:$P$4001,">="&$K$6,Cleaned_Data!$P$2:$P$4001,"<="&$K$7),NA()) -> 20366712 | X2: =IF(AND(OR(dashboard!$B$4="All",dashboard!$B$4=V2),OR(dashboard!$B$5="All",dashboard!$B$5=X$1)),SUMIFS(Cleaned_Data!$K$2:$K$4001,Cleaned_Data!$F$2:$F$4001,V2,Cleaned_Data!$E$2:$E$4001,X$1,Cleaned_Data!$G$2:$G$4001,$K$4,Cleaned_Data!$M$2:$M$4001,$K$5,Cleaned_Data!$P$2:$P$4001,">="&$K$6,Cleaned_Data!$P$2:$P$4001,"<="&$K$7),NA()) -> 10895017 | Y2: =IF(AND(OR(dashboard!$B$4="All",dashboard!$B$4=V2),OR(dashboard!$B$5="All",dashboard!$B$5=Y$1)),SUMIFS(Cleaned_Data!$K$2:$K$4001,Cleaned_Data!$F$2:$F$4001,V2,Cleaned_Data!$E$2:$E$4001,Y$1,Cleaned_Data!$G$2:$G$4001,$K$4,Cleaned_Data!$M$2:$M$4001,$K$5,Cleaned_Data!$P$2:$P$4001,">="&$K$6,Cleaned_Data!$P$2:$P$4001,"<="&$K$7),NA()) -> 5520621.7
A3: 2023-01 | C3: East | D3: Consumer | E3: Online | F3: Yes | G3: Accessories | H3: Total Transactions | I3: =COUNTIFS(Cleaned_Data!$A$2:$A$4001,"<>",Cleaned_Data!$F$2:$F$4001,$K$2,Cleaned_Data!$E$2:$E$4001,$K$3,Cleaned_Data!$G$2:$G$4001,$K$4,Cleaned_Data!$M$2:$M$4001,$K$5,Cleaned_Data!$P$2:$P$4001,">="&$K$6,Cleaned_Data!$P$2:$P$4001,"<="&$K$7) -> 987 | J3: Segment_Crit | K3: =IF(dashboard!$B$5="All","*",dashboard!$B$5) -> * | M3: 2023-01 | N3: =IF(AND(M3>=$K$6,M3<=$K$7),SUMIFS(Cleaned_Data!$K$2:$K$4001,Cleaned_Data!$F$2:$F$4001,$K$2,Cleaned_Data!$E$2:$E$4001,$K$3,Cleaned_Data!$G$2:$G$4001,$K$4,Cleaned_Data!$M$2:$M$4001,$K$5,Cleaned_Data!$P$2:$P$4001,M3),NA()) -> 2358298.7 | P3: Clothing | Q3: =SUMIFS(Cleaned_Data!$K$2:$K$4001,Cleaned_Data!$F$2:$F$4001,$K$2,Cleaned_Data!$E$2:$E$4001,$K$3,Cleaned_Data!$G$2:$G$4001,$K$4,Cleaned_Data!$M$2:$M$4001,$K$5,Cleaned_Data!$P$2:$P$4001,">="&$K$6,Cleaned_Data!$P$2:$P$4001,"<="&$K$7,Cleaned_Data!$H$2:$H$4001,P3) -> 1829356.1 | S3: Store | T3: =IF(OR(dashboard!$B$6="All",dashboard!$B$6=S3),SUMIFS(Cleaned_Data!$K$2:$K$4001,Cleaned_Data!$F$2:$F$4001,$K$2,Cleaned_Data!$E$2:$E$4001,$K$3,Cleaned_Data!$G$2:$G$4001,S3,Cleaned_Data!$M$2:$M$4001,$K$5,Cleaned_Data!$P$2:$P$4001,">="&$K$6,Cleaned_Data!$P$2:$P$4001,"<="&$K$7),NA()) -> 14502848 | V3: North | W3: =IF(AND(OR(dashboard!$B$4="All",dashboard!$B$4=V3),OR(dashboard!$B$5="All",dashboard!$B$5=W$1)),SUMIFS(Cleaned_Data!$K$2:$K$4001,Cleaned_Data!$F$2:$F$4001,V3,Cleaned_Data!$E$2:$E$4001,W$1,Cleaned_Data!$G$2:$G$4001,$K$4,Cleaned_Data!$M$2:$M$4001,$K$5,Cleaned_Data!$P$2:$P$4001,">="&$K$6,Cleaned_Data!$P$2:$P$4001,"<="&$K$7),NA()) -> #N/A | X3: =IF(AND(OR(dashboard!$B$4="All",dashboard!$B$4=V3),OR(dashboard!$B$5="All",dashboard!$B$5=X$1)),SUMIFS(Cleaned_Data!$K$2:$K$4001,Cleaned_Data!$F$2:$F$4001,V3,Cleaned_Data!$E$2:$E$4001,X$1,Cleaned_Data!$G$2:$G$4001,$K$4,Cleaned_Data!$M$2:$M$4001,$K$5,Cleaned_Data!$P$2:$P$4001,">="&$K$6,Cleaned_Data!$P$2:$P$4001,"<="&$K$7),NA()) -> #N/A | Y3: =IF(AND(OR(dashboard!$B$4="All",dashboard!$B$4=V3),OR(dashboard!$B$5="All",dashboard!$B$5=Y$1)),SUMIFS(Cleaned_Data!$K$2:$K$4001,Cleaned_Data!$F$2:$F$4001,V3,Cleaned_Data!$E$2:$E$4001,Y$1,Cleaned_Data!$G$2:$G$4001,$K$4,Cleaned_Data!$M$2:$M$4001,$K$5,Cleaned_Data!$P$2:$P$4001,">="&$K$6,Cleaned_Data!$P$2:$P$4001,"<="&$K$7),NA()) -> #N/A
A4: 2023-02 | C4: North | D4: Corporate | E4: Store | F4: No | G4: Clothing | H4: Distinct Customers | I4: =SUM(Cleaned_Data!$Q$2:$Q$4001) -> 570 | J4: Channel_Crit | K4: =IF(dashboard!$B$6="All","*",dashboard!$B$6) -> * | M4: 2023-02 | N4: =IF(AND(M4>=$K$6,M4<=$K$7),SUMIFS(Cleaned_Data!$K$2:$K$4001,Cleaned_Data!$F$2:$F$4001,$K$2,Cleaned_Data!$E$2:$E$4001,$K$3,Cleaned_Data!$G$2:$G$4001,$K$4,Cleaned_Data!$M$2:$M$4001,$K$5,Cleaned_Data!$P$2:$P$4001,M4),NA()) -> 1646030.9 | P4: Electronics | Q4: =SUMIFS(Cleaned_Data!$K$2:$K$4001,Cleaned_Data!$F$2:$F$4001,$K$2,Cleaned_Data!$E$2:$E$4001,$K$3,Cleaned_Data!$G$2:$G$4001,$K$4,Cleaned_Data!$M$2:$M$4001,$K$5,Cleaned_Data!$P$2:$P$4001,">="&$K$6,Cleaned_Data!$P$2:$P$4001,"<="&$K$7,Cleaned_Data!$H$2:$H$4001,P4) -> 10905712 | V4: South | W4: =IF(AND(OR(dashboard!$B$4="All",dashboard!$B$4=V4),OR(dashboard!$B$5="All",dashboard!$B$5=W$1)),SUMIFS(Cleaned_Data!$K$2:$K$4001,Cleaned_Data!$F$2:$F$4001,V4,Cleaned_Data!$E$2:$E$4001,W$1,Cleaned_Data!$G$2:$G$4001,$K$4,Cleaned_Data!$M$2:$M$4001,$K$5,Cleaned_Data!$P$2:$P$4001,">="&$K$6,Cleaned_Data!$P$2:$P$4001,"<="&$K$7),NA()) -> #N/A | X4: =IF(AND(OR(dashboard!$B$4="All",dashboard!$B$4=V4),OR(dashboard!$B$5="All",dashboard!$B$5=X$1)),SUMIFS(Cleaned_Data!$K$2:$K$4001,Cleaned_Data!$F$2:$F$4001,V4,Cleaned_Data!$E$2:$E$4001,X$1,Cleaned_Data!$G$2:$G$4001,$K$4,Cleaned_Data!$M$2:$M$4001,$K$5,Cleaned_Data!$P$2:$P$4001,">="&$K$6,Cleaned_Data!$P$2:$P$4001,"<="&$K$7),NA()) -> #N/A | Y4: =IF(AND(OR(dashboard!$B$4="All",dashboard!$B$4=V4),OR(dashboard!$B$5="All",dashboard!$B$5=Y$1)),SUMIFS(Cleaned_Data!$K$2:$K$4001,Cleaned_Data!$F$2:$F$4001,V4,Cleaned_Data!$E$2:$E$4001,Y$1,Cleaned_Data!$G$2:$G$4001,$K$4,Cleaned_Data!$M$2:$M$4001,$K$5,Cleaned_Data!$P$2:$P$4001,">="&$K$6,Cleaned_Data!$P$2:$P$4001,"<="&$K$7),NA()) -> #N/A
A5: 2023-03 | C5: South | D5: Home Office | G5: Electronics | H5: Returned Transactions | I5: =COUNTIFS(Cleaned_Data!$A$2:$A$4001,"<>",Cleaned_Data!$F$2:$F$4001,$K$2,Cleaned_Data!$E$2:$E$4001,$K$3,Cleaned_Data!$G$2:$G$4001,$K$4,Cleaned_Data!$M$2:$M$4001,"Yes",Cleaned_Data!$P$2:$P$4001,">="&$K$6,Cleaned_Data!$P$2:$P$4001,"<="&$K$7) -> 118 | J5: Return_Crit | K5: =IF(dashboard!$B$7="All","*",dashboard!$B$7) -> * | M5: 2023-03 | N5: =IF(AND(M5>=$K$6,M5<=$K$7),SUMIFS(Cleaned_Data!$K$2:$K$4001,Cleaned_Data!$F$2:$F$4001,$K$2,Cleaned_Data!$E$2:$E$4001,$K$3,Cleaned_Data!$G$2:$G$4001,$K$4,Cleaned_Data!$M$2:$M$4001,$K$5,Cleaned_Data!$P$2:$P$4001,M5),NA()) -> 1757681.3 | P5: Furniture | Q5: =SUMIFS(Cleaned_Data!$K$2:$K$4001,Cleaned_Data!$F$2:$F$4001,$K$2,Cleaned_Data!$E$2:$E$4001,$K$3,Cleaned_Data!$G$2:$G$4001,$K$4,Cleaned_Data!$M$2:$M$4001,$K$5,Cleaned_Data!$P$2:$P$4001,">="&$K$6,Cleaned_Data!$P$2:$P$4001,"<="&$K$7,Cleaned_Data!$H$2:$H$4001,P5) -> 23163141 | V5: West | W5: =IF(AND(OR(dashboard!$B$4="All",dashboard!$B$4=V5),OR(dashboard!$B$5="All",dashboard!$B$5=W$1)),SUMIFS(Cleaned_Data!$K$2:$K$4001,Cleaned_Data!$F$2:$F$4001,V5,Cleaned_Data!$E$2:$E$4001,W$1,Cleaned_Data!$G$2:$G$4001,$K$4,Cleaned_Data!$M$2:$M$4001,$K$5,Cleaned_Data!$P$2:$P$4001,">="&$K$6,Cleaned_Data!$P$2:$P$4001,"<="&$K$7),NA()) -> #N/A | X5: =IF(AND(OR(dashboard!$B$4="All",dashboard!$B$4=V5),OR(dashboard!$B$5="All",dashboard!$B$5=X$1)),SUMIFS(Cleaned_Data!$K$2:$K$4001,Cleaned_Data!$F$2:$F$4001,V5,Cleaned_Data!$E$2:$E$4001,X$1,Cleaned_Data!$G$2:$G$4001,$K$4,Cleaned_Data!$M$2:$M$4001,$K$5,Cleaned_Data!$P$2:$P$4001,">="&$K$6,Cleaned_Data!$P$2:$P$4001,"<="&$K$7),NA()) -> #N/A | Y5: =IF(AND(OR(dashboard!$B$4="All",dashboard!$B$4=V5),OR(dashboard!$B$5="All",dashboard!$B$5=Y$1)),SUMIFS(Cleaned_Data!$K$2:$K$4001,Cleaned_Data!$F$2:$F$4001,V5,Cleaned_Data!$E$2:$E$4001,Y$1,Cleaned_Data!$G$2:$G$4001,$K$4,Cleaned_Data!$M$2:$M$4001,$K$5,Cleaned_Data!$P$2:$P$4001,">="&$K$6,Cleaned_Data!$P$2:$P$4001,"<="&$K$7),NA()) -> #N/A
A6: 2023-04 | C6: West | G6: Furniture | H6: Return Rate | I6: =IF(I3=0,"",I5/I3) -> 0.1195542 | J6: From_Month | K6: =dashboard!$B$8 -> 2023-01 | M6: 2023-04 | N6: =IF(AND(M6>=$K$6,M6<=$K$7),SUMIFS(Cleaned_Data!$K$2:$K$4001,Cleaned_Data!$F$2:$F$4001,$K$2,Cleaned_Data!$E$2:$E$4001,$K$3,Cleaned_Data!$G$2:$G$4001,$K$4,Cleaned_Data!$M$2:$M$4001,$K$5,Cleaned_Data!$P$2:$P$4001,M6),NA()) -> 2760048.2
A7: 2023-05 | H7: Avg Rev / Transaction | I7: =IF(I3=0,"",I2/I3) -> 37266.819 | J7: To_Month | K7: =dashboard!$B$9 -> 2024-06 | M7: 2023-05 | N7: =IF(AND(M7>=$K$6,M7<=$K$7),SUMIFS(Cleaned_Data!$K$2:$K$4001,Cleaned_Data!$F$2:$F$4001,$K$2,Cleaned_Data!$E$2:$E$4001,$K$3,Cleaned_Data!$G$2:$G$4001,$K$4,Cleaned_Data!$M$2:$M$4001,$K$5,Cleaned_Data!$P$2:$P$4001,M7),NA()) -> 2328738.2
A8: 2023-06 | H8: Avg Rev / Customer | I8: =IF(I4=0,"",I2/I4) -> 64530.44 | M8: 2023-06 | N8: =IF(AND(M8>=$K$6,M8<=$K$7),SUMIFS(Cleaned_Data!$K$2:$K$4001,Cleaned_Data!$F$2:$F$4001,$K$2,Cleaned_Data!$E$2:$E$4001,$K$3,Cleaned_Data!$G$2:$G$4001,$K$4,Cleaned_Data!$M$2:$M$4001,$K$5,Cleaned_Data!$P$2:$P$4001,M8),NA()) -> 2378308.6
A9: 2023-07 | M9: 2023-07 | N9: =IF(AND(M9>=$K$6,M9<=$K$7),SUMIFS(Cleaned_Data!$K$2:$K$4001,Cleaned_Data!$F$2:$F$4001,$K$2,Cleaned_Data!$E$2:$E$4001,$K$3,Cleaned_Data!$G$2:$G$4001,$K$4,Cleaned_Data!$M$2:$M$4001,$K$5,Cleaned_Data!$P$2:$P$4001,M9),NA()) -> 2528085.4
A10: 2023-08 | M10: 2023-08 | N10: =IF(AND(M10>=$K$6,M10<=$K$7),SUMIFS(Cleaned_Data!$K$2:$K$4001,Cleaned_Data!$F$2:$F$4001,$K$2,Cleaned_Data!$E$2:$E$4001,$K$3,Cleaned_Data!$G$2:$G$4001,$K$4,Cleaned_Data!$M$2:$M$4001,$K$5,Cleaned_Data!$P$2:$P$4001,M10),NA()) -> 2140343.6
A11: 2023-09 | M11: 2023-09 | N11: =IF(AND(M11>=$K$6,M11<=$K$7),SUMIFS(Cleaned_Data!$K$2:$K$4001,Cleaned_Data!$F$2:$F$4001,$K$2,Cleaned_Data!$E$2:$E$4001,$K$3,Cleaned_Data!$G$2:$G$4001,$K$4,Cleaned_Data!$M$2:$M$4001,$K$5,Cleaned_Data!$P$2:$P$4001,M11),NA()) -> 1512245.4
A12: 2023-10 | M12: 2023-10 | N12: =IF(AND(M12>=$K$6,M12<=$K$7),SUMIFS(Cleaned_Data!$K$2:$K$4001,Cleaned_Data!$F$2:$F$4001,$K$2,Cleaned_Data!$E$2:$E$4001,$K$3,Cleaned_Data!$G$2:$G$4001,$K$4,Cleaned_Data!$M$2:$M$4001,$K$5,Cleaned_Data!$P$2:$P$4001,M12),NA()) -> 1905870.8
A13: 2023-11 | M13: 2023-11 | N13: =IF(AND(M13>=$K$6,M13<=$K$7),SUMIFS(Cleaned_Data!$K$2:$K$4001,Cleaned_Data!$F$2:$F$4001,$K$2,Cleaned_Data!$E$2:$E$4001,$K$3,Cleaned_Data!$G$2:$G$4001,$K$4,Cleaned_Data!$M$2:$M$4001,$K$5,Cleaned_Data!$P$2:$P$4001,M13),NA()) -> 2408232.2
A14: 2023-12 | M14: 2023-12 | N14: =IF(AND(M14>=$K$6,M14<=$K$7),SUMIFS(Cleaned_Data!$K$2:$K$4001,Cleaned_Data!$F$2:$F$4001,$K$2,Cleaned_Data!$E$2:$E$4001,$K$3,Cleaned_Data!$G$2:$G$4001,$K$4,Cleaned_Data!$M$2:$M$4001,$K$5,Cleaned_Data!$P$2:$P$4001,M14),NA()) -> 2096701.1
A15: 2024-01 | M15: 2024-01 | N15: =IF(AND(M15>=$K$6,M15<=$K$7),SUMIFS(Cleaned_Data!$K$2:$K$4001,Cleaned_Data!$F$2:$F$4001,$K$2,Cleaned_Data!$E$2:$E$4001,$K$3,Cleaned_Data!$G$2:$G$4001,$K$4,Cleaned_Data!$M$2:$M$4001,$K$5,Cleaned_Data!$P$2:$P$4001,M15),NA()) -> 1763795.6
A16: 2024-02 | M16: 2024-02 | N16: =IF(AND(M16>=$K$6,M16<=$K$7),SUMIFS(Cleaned_Data!$K$2:$K$4001,Cleaned_Data!$F$2:$F$4001,$K$2,Cleaned_Data!$E$2:$E$4001,$K$3,Cleaned_Data!$G$2:$G$4001,$K$4,Cleaned_Data!$M$2:$M$4001,$K$5,Cleaned_Data!$P$2:$P$4001,M16),NA()) -> 1706175.6
A17: 2024-03 | M17: 2024-03 | N17: =IF(AND(M17>=$K$6,M17<=$K$7),SUMIFS(Cleaned_Data!$K$2:$K$4001,Cleaned_Data!$F$2:$F$4001,$K$2,Cleaned_Data!$E$2:$E$4001,$K$3,Cleaned_Data!$G$2:$G$4001,$K$4,Cleaned_Data!$M$2:$M$4001,$K$5,Cleaned_Data!$P$2:$P$4001,M17),NA()) -> 1441957.5
A18: 2024-04 | M18: 2024-04 | N18: =IF(AND(M18>=$K$6,M18<=$K$7),SUMIFS(Cleaned_Data!$K$2:$K$4001,Cleaned_Data!$F$2:$F$4001,$K$2,Cleaned_Data!$E$2:$E$4001,$K$3,Cleaned_Data!$G$2:$G$4001,$K$4,Cleaned_Data!$M$2:$M$4001,$K$5,Cleaned_Data!$P$2:$P$4001,M18),NA()) -> 2277472.7
A19: 2024-05 | M19: 2024-05 | N19: =IF(AND(M19>=$K$6,M19<=$K$7),SUMIFS(Cleaned_Data!$K$2:$K$4001,Cleaned_Data!$F$2:$F$4001,$K$2,Cleaned_Data!$E$2:$E$4001,$K$3,Cleaned_Data!$G$2:$G$4001,$K$4,Cleaned_Data!$M$2:$M$4001,$K$5,Cleaned_Data!$P$2:$P$4001,M19),NA()) -> 2145829.1
A20: 2024-06 | M20: 2024-06 | N20: =IF(AND(M20>=$K$6,M20<=$K$7),SUMIFS(Cleaned_Data!$K$2:$K$4001,Cleaned_Data!$F$2:$F$4001,$K$2,Cleaned_Data!$E$2:$E$4001,$K$3,Cleaned_Data!$G$2:$G$4001,$K$4,Cleaned_Data!$M$2:$M$4001,$K$5,Cleaned_Data!$P$2:$P$4001,M20),NA()) -> 1626535.9
